MANIFEST.in
ez_setup.py
setup.py
django_seo_cascade.egg-info/PKG-INFO
django_seo_cascade.egg-info/SOURCES.txt
django_seo_cascade.egg-info/dependency_links.txt
django_seo_cascade.egg-info/requires.txt
django_seo_cascade.egg-info/top_level.txt
seo_cascade/__init__.py
seo_cascade/admin.py
seo_cascade/middleware.py
seo_cascade/models.py
seo_cascade/signals.py
seo_cascade/tests.py
seo_cascade/util.py
seo_cascade/views.py
seo_cascade/management/__init__.py
seo_cascade/management/commands/__init__.py
seo_cascade/management/commands/flush_sitemap.py
seo_cascade/migrations/0001_initial.py
seo_cascade/migrations/0002_auto__add_seolocation__add_field_seopageoverride_changefreq__add_field.py
seo_cascade/migrations/__init__.py
seo_cascade/templatetags/__init__.py
seo_cascade/templatetags/meta.py