Metadata-Version: 1.0
Name: django-seo-cascade
Version: 0.5
Summary: Django SEO manager. Automatic sitemap generation, cascading meta tag blocks, and overrides via the django admin.
Home-page: https://github.com/thisismess/django-seo-cascade
Author: Lynn Dylan Hurley, Jack Shedd
Author-email: lynn.dylan.hurley@gmail.com
License: UNKNOWN
Platform: UNKNOWN
